pastro/__init__.py
pastro/answer_sheet.py
pastro/catalog.py
pastro/constants.py
pastro/horizons.py
pastro/io.py
pastro/old_types.py
pastro/pck.py
pastro/plot_utils.py
pastro/propagator.py
pastro/py.typed
pastro/utils.py
pastro/analytical/__init__.py
pastro/analytical/analytical.py
pastro/forces/__init__.py
pastro/forces/atmosphere.py
pastro/forces/base.py
pastro/forces/drag.py
pastro/forces/gravity.py
pastro/forces/srp.py
pastro/forces/third_body.py
pastro/optimize/__init__.py
pastro/optimize/gradient.py
pastro/optimize/utils.py
pastro/plots/__init__.py
pastro/plots/config.py
pastro/plots/core.py
pastro/plots/other.py
pastro/plots/state.py
pastro/root_finding/__init__.py
pastro/root_finding/enrke.py
pastro/solvers/__init__.py
pastro/solvers/base.py
pastro/solvers/euler.py
pastro/solvers/rk.py
pastro/tests/__init__.py
pastro/tests/test_types.py
pastro/tests/test_utils.py
pastro/tests/types/__init__.py
pastro/tests/types/test_KeplerianState.py
pastro/types/__init__.py
pastro/types/conversion.py
pastro/types/new_types.py
pastro/types/types.py
nastro-0.1.0.dist-info/METADATA
nastro-0.1.0.dist-info/WHEEL
nastro-0.1.0.dist-info/top_level.txt
nastro-0.1.0.dist-info/RECORD
